mnist_classifier/__init__.py
mnist_classifier/algorithm_meta.py
mnist_classifier/dataset.py
mnist_classifier/mlp.py
mnist_classifier/predict.py
mnist_classifier/random_forest.py
mnist_classifier/report_manager.py
mnist_classifier/visualizer.py
tests/__init__.py
tests/algo_test_master.py
tests/test_dataset.py
tests/test_mlp.py
tests/test_predict.py
tests/test_reports.py
tests/test_rf.py
tests/test_visualizer.py
mnist_classifier-1.0.4.dist-info/LICENSE
mnist_classifier-1.0.4.dist-info/METADATA
mnist_classifier-1.0.4.dist-info/WHEEL
mnist_classifier-1.0.4.dist-info/entry_points.txt
mnist_classifier-1.0.4.dist-info/top_level.txt
mnist_classifier-1.0.4.dist-info/RECORD
