Metadata-Version: 2.1
Name: mnist-classifier
Version: 1.0.4
Summary: Basic mnist classifier example of a Reproducible Research Project in Python
Home-page: https://github.com/sandrich/classifying_digits_mnist
Author: Christian Sandrini
Author-email: mail@chrissandrini.ch
License: MIT
Platform: UNKNOWN
Classifier: Development Status :: 4 - Beta
Classifier: Intended Audience :: Developers
Classifier: License :: OSI Approved :: MIT License
Classifier: Natural Language :: English
Classifier: Programming Language :: Python
Classifier: Programming Language :: Python :: 3
Classifier: Topic :: Software Development :: Libraries :: Python Modules
Requires-Dist: setuptools
Requires-Dist: scikit-learn (==0.23.2)
Requires-Dist: numpy (==1.19.1)
Requires-Dist: requests (==2.24.0)
Requires-Dist: matplotlib (==3.3.1)
Requires-Dist: pandas (==1.1.2)
Requires-Dist: pytest-runner (==5.2)
Requires-Dist: python-dateutil (==2.8.1)
